<?xml version="1.0" encoding="euc-kr" ?>

<decorators defaultdir="/decorator">
  <decorator name="mypage" page="decorator_mypage.jsp">
     <pattern>/user/mypage/*</pattern>
  </decorator>
  <decorator name="main" page="decorator.jsp">
     <pattern>*.jsy</pattern>
  </decorator>
  <!-- layout 설정을 제외 함. -->
  <excludes>
  	<pattern>/hire/companyDetail.jsy*</pattern>
  	<pattern>/message/*</pattern>
  	<pattern>/user/findpassword.jsy</pattern>
  	<pattern>/user/mypage/manageuser_ajax.jsy*</pattern>
  </excludes>
</decorators>